mozilla_taskgraph/__init__.py
mozilla_taskgraph/config.py
mozilla_taskgraph/version.py
mozilla_taskgraph/worker_types.py
mozilla_taskgraph/actions/__init__.py
mozilla_taskgraph/actions/release_promotion.py
mozilla_taskgraph/transforms/__init__.py
mozilla_taskgraph/transforms/replicate.py
mozilla_taskgraph/transforms/scriptworker/__init__.py
mozilla_taskgraph/transforms/scriptworker/release_artifacts.py
mozilla_taskgraph/transforms/scriptworker/shipit/__init__.py
mozilla_taskgraph/transforms/scriptworker/shipit/mark_as_shipped.py
mozilla_taskgraph/util/signed_artifacts.py
mozilla_taskgraph-3.4.2.dist-info/METADATA
mozilla_taskgraph-3.4.2.dist-info/WHEEL
mozilla_taskgraph-3.4.2.dist-info/licenses/LICENSE
mozilla_taskgraph-3.4.2.dist-info/RECORD
