Metadata-Version: 2.4
Name: mozilla-taskgraph
Version: 3.4.2
Summary: Mozilla specific transforms and utilities for Taskgraph
Project-URL: Repository, https://github.com/mozilla-releng/mozilla-taskgraph
Project-URL: Issues, https://github.com/mozilla-releng/mozilla-taskgraph/issues
Author-email: Mozilla Release Engineering <release+mozilla-taskgraph@mozilla.com>
License-File: LICENSE
Classifier: Development Status :: 4 - Beta
Classifier: Environment :: Console
Classifier: License :: OSI Approved :: Mozilla Public License 2.0 (MPL 2.0)
Classifier: Programming Language :: Python :: 3.8
Classifier: Programming Language :: Python :: 3.9
Classifier: Programming Language :: Python :: 3.10
Classifier: Programming Language :: Python :: 3.11
Classifier: Programming Language :: Python :: 3.12
Classifier: Topic :: Software Development
Requires-Python: >=3.8
Requires-Dist: taskcluster-taskgraph<17,>=11
